falcon_url/__init__.py
falcon_url/param.py
falcon_url/py.typed
falcon_url/route.py
falcon_url/router.py
falcon_url/template.py
falcon_url/url.py
falcon_url-0.1.1.dist-info/licenses/LICENSE
falcon_url-0.1.1.dist-info/WHEEL
falcon_url-0.1.1.dist-info/METADATA
falcon_url-0.1.1.dist-info/RECORD
