Metadata-Version: 2.4
Name: falcon-url
Version: 0.1.1
Summary: Falcon router with url_for-like support
Author: jkmnt
Requires-Python: >=3.12
Classifier: Programming Language :: Python :: 3
Classifier: License :: OSI Approved :: MIT License
Classifier: Operating System :: OS Independent
License-File: LICENSE
Requires-Dist: falcon >= 4.0.2
Project-URL: Source, https://github.com/jkmnt/falcon-url
